MANIFEST.in
README.md
setup.cfg
setup.py
versioneer.py
avionix/__init__.py
avionix/_process_utils.py
avionix/_version.py
avionix/conftest.py
avionix/errors.py
avionix/options.py
avionix/py.typed
avionix.egg-info/PKG-INFO
avionix.egg-info/SOURCES.txt
avionix.egg-info/dependency_links.txt
avionix.egg-info/not-zip-safe
avionix.egg-info/requires.txt
avionix.egg-info/top_level.txt
avionix/chart/__init__.py
avionix/chart/chart_builder.py
avionix/chart/chart_dependency.py
avionix/chart/chart_info.py
avionix/chart/chart_maintainer.py
avionix/chart/utils.py
avionix/chart/values_yaml.py
avionix/kube/__init__.py
avionix/kube/admissionregistration.py
avionix/kube/apiextensions.py
avionix/kube/apiregistration.py
avionix/kube/apps.py
avionix/kube/authentication.py
avionix/kube/authorization.py
avionix/kube/autoscaling.py
avionix/kube/base_objects.py
avionix/kube/batch.py
avionix/kube/certificates.py
avionix/kube/coordination.py
avionix/kube/core.py
avionix/kube/discovery.py
avionix/kube/extensions.py
avionix/kube/meta.py
avionix/kube/networking.py
avionix/kube/node.py
avionix/kube/policy.py
avionix/kube/rbac_authorization.py
avionix/kube/reference.py
avionix/kube/scheduling.py
avionix/kube/storage.py
avionix/testing/__init__.py
avionix/testing/helpers.py
avionix/testing/installation_context.py
avionix/yaml/__init__.py
avionix/yaml/yaml_handling.py